qwiic_adxl313.py
sparkfun_qwiic_adxl313-0.0.7.dist-info/LICENSE
sparkfun_qwiic_adxl313-0.0.7.dist-info/METADATA
sparkfun_qwiic_adxl313-0.0.7.dist-info/WHEEL
sparkfun_qwiic_adxl313-0.0.7.dist-info/top_level.txt
sparkfun_qwiic_adxl313-0.0.7.dist-info/RECORD
